Metadata-Version: 2.1
Name: datelist-sdk-python
Version: 1.0.0
Summary: SDK for https://datelist.io in Python
Home-page: https://datelist.io
Author: Alexis Clarembeau
Author-email: contact@datelist.io
License: MIT
Platform: UNKNOWN
